{"inkVersion":21,"root":[[{"->":"RileyIgnored"},["done",{"#f":5,"#n":"g-0"}],null],"done",{"RileyIgnored":[["^You Ignored Riley :( ","#","^speaker:Riley ","/#","#","^portrait:riley ","/#","#","^layout:left","/#","\n","^You are a bad person ","#","^speaker:Riley ","/#","#","^portrait:riley ","/#","#","^layout:left","/#","\n",["ev",{"^->":"RileyIgnored.0.22.$r1"},{"temp=":"$r"},"str",{"->":".^.s"},[{"#n":"$r1"}],"/str","/ev",{"*":".^.^.c-0","flg":18},{"s":["^I am sorry Riley :( ","#","^speaker:Player ","/#","#","^portrait:player ","/#","#","^layout:right","/#",{"->":"$r","var":true},null]}],{"c-0":["ev",{"^->":"RileyIgnored.0.c-0.$r2"},"/ev",{"temp=":"$r"},{"->":".^.^.22.s"},[{"#n":"$r2"}],"\n","^The bad ending ","#","^speaker:Riley ","/#","#","^portrait:riley ","/#","#","^layout:left","/#","\n","end",{"#f":5}]}],{"#f":1}],"#f":1}],"listDefs":{}}